<Properties StartupConfiguration="{3420ACFB-EED6-4A20-8DC2-A7EBD7A1A86D}|http">
  <MonoDevelop.Ide.DebuggingService.PinnedWatches />
  <MultiItemStartupConfigurations />
  <MonoDevelop.Ide.Workspace ActiveConfiguration="Debug" />
  <MonoDevelop.Ide.ItemProperties.PaymnetAPI PreferredExecutionTarget="/Applications/Firefox.app" FirstBuild="True" />
  <MonoDevelop.Ide.Workbench ActiveDocument="Models/PaymentDetail.cs">
    <Files>
      <File FileName="Models/PaymentDetail.cs" Line="16" Column="1" />
    </Files>
    <Pads>
      <Pad Id="ProjectPad">
        <State name="__root__" />
      </Pad>
    </Pads>
  </MonoDevelop.Ide.Workbench>
  <MonoDevelop.Ide.DebuggingService.Breakpoints>
    <BreakpointStore />
  </MonoDevelop.Ide.DebuggingService.Breakpoints>
</Properties>